<?xml version="1.0" encoding="utf-8" ?><dwsync><file name="bubble.gif" server="server147.web-hosting.com//public_html/" local="3414974400" remote="16299876288" /><file name="cpanel.gif" server="server147.web-hosting.com//public_html/" local="3414974400" remote="16299876288" /><file name="curve-bot.gif" server="server147.web-hosting.com//public_html/" local="3414974400" remote="16299876288" /><file name="curve-top.gif" server="server147.web-hosting.com//public_html/" local="3414974400" remote="16299876288" /><file name="email.gif" server="server147.web-hosting.com//public_html/" local="3414974400" remote="16299876288" /><file name="globe.gif" server="server147.web-hosting.com//public_html/" local="3414974400" remote="16299876288" /><file name="messenger.gif" server="server147.web-hosting.com//public_html/" local="3414974400" remote="16299876288" /><file name="news.gif" server="server147.web-hosting.com//public_html/" local="3414974400" remote="16299876288" /><file name="support.gif" server="server147.web-hosting.com//public_html/" local="3414974400" remote="16299876288" /><file name="video.gif" server="server147.web-hosting.com//public_html/" local="3414974400" remote="16299876288" /></dwsync>